setup.py
sendslack/__init__.py
sendslack.egg-info/PKG-INFO
sendslack.egg-info/SOURCES.txt
sendslack.egg-info/dependency_links.txt
sendslack.egg-info/requires.txt
sendslack.egg-info/top_level.txt