Metadata-Version: 1.0
Name: sendslack
Version: 0.0.1
Summary: send slack to channel every where
Home-page: https://github.com/hongkunyoo/sendslack
Author: coffeewhale
Author-email: hongkunyoo@gmail.com
License: MIT License
Keywords: slack api,slack notification
Platform: UNKNOWN
